talkgpt4all/__init__.py
talkgpt4all/chat.py
talkgpt4all-2.5.0.dist-info/METADATA
talkgpt4all-2.5.0.dist-info/WHEEL
talkgpt4all-2.5.0.dist-info/entry_points.txt
talkgpt4all-2.5.0.dist-info/licenses/LICENSE
talkgpt4all-2.5.0.dist-info/RECORD
