Metadata-Version: 2.1
Name: talkgpt4all
Version: 2.5.0
Summary: A voice chatbot based on GPT4All and OpenAI Whisper, running on your PC locally
Project-URL: Homepage, https://github.com/vra/talkGPT4All
Project-URL: Bug Tracker, https://github.com/vra/talkGPT4All/issues
Author-email: Yunfeng Wang <wyf.brz@gmail.com>
License-File: LICENSE
Classifier: License :: OSI Approved :: MIT License
Classifier: Operating System :: OS Independent
Classifier: Programming Language :: Python :: 3
Requires-Python: >=3.7
Requires-Dist: gpt4all
Requires-Dist: openai-whisper
Requires-Dist: playsound
Requires-Dist: speechrecognition
Requires-Dist: tts
